tiling/tests.py
tiling/__init__.py
python_tiling-0.1.0.dist-info/DESCRIPTION.rst
python_tiling-0.1.0.dist-info/RECORD
python_tiling-0.1.0.dist-info/metadata.json
python_tiling-0.1.0.dist-info/WHEEL
python_tiling-0.1.0.dist-info/dependency_links.txt
python_tiling-0.1.0.dist-info/METADATA
python_tiling-0.1.0.dist-info/top_level.txt
