Metadata-Version: 2.0
Name: python-tiling
Version: 0.1.0
Summary: Geographic tiling library for Python.
Home-page: http://seanhayes.name/
Author: Seán Hayes
Author-email: sean@seanhayes.name
License: BSD
Download-URL: https://github.com/SeanHayes/python-tiling
Keywords: gis geo tiling bounding box
Platform: UNKNOWN
Classifier: Development Status :: 3 - Alpha
Classifier: Intended Audience :: Developers
Classifier: License :: OSI Approved :: BSD License
Classifier: Operating System :: OS Independent
Classifier: Programming Language :: Python
Classifier: Programming Language :: Python :: 2.7
Classifier: Topic :: Internet :: WWW/HTTP :: Dynamic Content
Classifier: Topic :: Software Development :: Libraries
Classifier: Topic :: Software Development :: Libraries :: Python Modules
Provides-Extra: decimal
Requires-Dist: dmath (==0.9.1); extra == 'decimal'
